config/__init__.py
config/_config.py
config/_dicts.py
config/_errors.py
config/_gsm.py
config/_yaml.py
ez_yaml_config-0.4.2.dist-info/METADATA
ez_yaml_config-0.4.2.dist-info/WHEEL
ez_yaml_config-0.4.2.dist-info/top_level.txt
ez_yaml_config-0.4.2.dist-info/RECORD
