Metadata-Version: 2.4
Name: ez-yaml-config
Version: 0.4.2
Summary: Typed config files
Project-URL: Homepage, https://github.com/quarterzip/ez-yaml-config
Project-URL: Issues, https://github.com/quarterzip/ez-yaml-config/issues
Classifier: Operating System :: OS Independent
Classifier: Programming Language :: Python :: 3
Requires-Python: >=3.13
Requires-Dist: pyyaml>=6.0.2
Requires-Dist: pydantic>=2.11.4
Requires-Dist: google-cloud-secret-manager>=2.23.3
Requires-Dist: google-crc32c>=1.7.1
Provides-Extra: dev
Requires-Dist: pre-commit>=4.2.0; extra == "dev"
Requires-Dist: pylint>=3.3.6; extra == "dev"
Requires-Dist: ruff==0.12.0; extra == "dev"
Requires-Dist: uv==0.7.13; extra == "dev"
